DGB/__init__.py
DGB/download.py
DGB/evaluator.py
DGB/__pycache__/__init__.cpython-39.pyc
DGB/__pycache__/download.cpython-39.pyc
DGB/__pycache__/evaluator.cpython-39.pyc
dgb-0.2.dist-info/METADATA
dgb-0.2.dist-info/WHEEL
dgb-0.2.dist-info/top_level.txt
dgb-0.2.dist-info/RECORD
